pianoray/__init__.py
pianoray/__main__.py
pianoray/cpp.py
pianoray/logger.py
pianoray/utils.py
pianoray/api/__init__.py
pianoray/api/accessor.py
pianoray/api/default.py
pianoray/api/importer.py
pianoray/api/interpolate.py
pianoray/api/keyframe.py
pianoray/api/modifiers.py
pianoray/api/pgroup.py
pianoray/api/props.py
pianoray/api/scene.py
pianoray/cutils/blocks.cpp
pianoray/cutils/glare.cpp
pianoray/cutils/keyboard.cpp
pianoray/cutils/particles.cpp
pianoray/cutils/pr_image.hpp
pianoray/cutils/pr_math.hpp
pianoray/cutils/pr_piano.hpp
pianoray/cutils/pr_random.hpp
pianoray/effects/__init__.py
pianoray/effects/blocks.py
pianoray/effects/effect.py
pianoray/effects/glare.py
pianoray/effects/keyboard.py
pianoray/effects/midi.py
pianoray/effects/particles.py
pianoray/render/__init__.py
pianoray/render/lib.py
pianoray/render/render.py
pianoray/render/video.py
pianoray/view/__init__.py
pianoray/view/info.py
pianoray/view/preview.py
pianoray/view/timeline.py
pianoray/view/utils.py
pianoray/view/video.py
pianoray/view/viewer.py
pianoray-0.2.3.dist-info/LICENSE
pianoray-0.2.3.dist-info/METADATA
pianoray-0.2.3.dist-info/WHEEL
pianoray-0.2.3.dist-info/entry_points.txt
pianoray-0.2.3.dist-info/top_level.txt
pianoray-0.2.3.dist-info/RECORD
