Metadata-Version: 2.1
Name: pianoray
Version: 0.2.3
Summary: Piano performance visualizer.
Home-page: https://github.com/phuang1024/pianoray
Author: PianoRay Authors
Author-email: phuang1024@gmail.com
License: UNKNOWN
Platform: UNKNOWN
Classifier: Programming Language :: Python :: 3
Classifier: License :: OSI Approved :: GNU General Public License v3 or later (GPLv3+)
Classifier: Operating System :: OS Independent
Requires-Dist: mido
Requires-Dist: numpy
Requires-Dist: opencv-python
Requires-Dist: pygame
Requires-Dist: sphinx
Requires-Dist: sphinx-rtd-theme
Requires-Dist: termcolor
Requires-Dist: tqdm
Requires-Dist: wheel
